yh_password/__init__.py
yh_password/core.py
yh_password-0.1.0.dist-info/METADATA
yh_password-0.1.0.dist-info/WHEEL
yh_password-0.1.0.dist-info/top_level.txt
yh_password-0.1.0.dist-info/RECORD
