Metadata-Version: 2.4
Name: yh_password
Version: 0.1.0
Summary: Simple password creator utilities
Author-email: yh <yh.siegen@gmail.com>
License: MIT
Project-URL: Homepage, https://github.com/word119/yh_password
Keywords: password,generator,utilities
Classifier: Programming Language :: Python :: 3
Classifier: License :: OSI Approved :: MIT License
Classifier: Operating System :: OS Independent
Requires-Python: >=3.10
